CORScanner/.gitignore
CORScanner/LICENSE
CORScanner/MANIFEST.in
CORScanner/README.md
CORScanner/__init__.py
CORScanner/cors_scan.py
CORScanner/origins.json
CORScanner/requirements.txt
CORScanner/setup.py
CORScanner/top_100_domains.txt
CORScanner/build/lib/common/__init__.py
CORScanner/build/lib/common/common.py
CORScanner/build/lib/common/corscheck.py
CORScanner/build/lib/common/logger.py
CORScanner/common/__init__.py
CORScanner/common/common.py
CORScanner/common/corscheck.py
CORScanner/common/logger.py
CORScanner/cors.egg-info/PKG-INFO
CORScanner/cors.egg-info/SOURCES.txt
CORScanner/cors.egg-info/dependency_links.txt
CORScanner/cors.egg-info/entry_points.txt
CORScanner/cors.egg-info/not-zip-safe
CORScanner/cors.egg-info/requires.txt
CORScanner/cors.egg-info/top_level.txt
CORScanner/dist/cors-0.9.6-py3.9.egg
CORScanner/images/screenshot.png
CORScanner/images/walmart.png
corscanner-0.9.7.dist-info/METADATA
corscanner-0.9.7.dist-info/WHEEL
corscanner-0.9.7.dist-info/entry_points.txt
corscanner-0.9.7.dist-info/top_level.txt
corscanner-0.9.7.dist-info/RECORD
